docs/source/conf.py
docs/source/contrib.rst
docs/source/index.rst
docs/source/_static/custom.css
docs/source/_static/quick_start_ez.png
docs/source/api/postprocess.rst
docs/source/api/sim_diag.rst
docs/source/api/utilities.rst
examples/edited-deck.1d
examples/example_Derivatives.ipynb
examples/example_FFT.ipynb
examples/example_InputDeck.ipynb
examples/example_Simulation_Diagnostic.ipynb
examples/quick_start.ipynb
examples/quick_start.py
examples/example_data/run-info
examples/example_data/thermal.1d
examples/example_data/HIST/fld_ene
examples/example_data/HIST/par01_ene
examples/example_data/HIST/par01_temp
examples/example_data/MS/run-info
examples/example_data/MS/DENSITY/electrons/charge/charge-electrons-000000.h5
examples/example_data/MS/DENSITY/electrons/charge/charge-electrons-000001.h5
examples/example_data/MS/DENSITY/electrons/charge/charge-electrons-000002.h5
examples/example_data/MS/DENSITY/electrons/charge/charge-electrons-000003.h5
examples/example_data/MS/DENSITY/electrons/charge/charge-electrons-000004.h5
examples/example_data/MS/DENSITY/electrons/charge/charge-electrons-000005.h5
examples/example_data/MS/DENSITY/electrons/charge/charge-electrons-000006.h5
examples/example_data/MS/DENSITY/electrons/charge/charge-electrons-000007.h5
examples/example_data/MS/DENSITY/electrons/charge/charge-electrons-000008.h5
examples/example_data/MS/DENSITY/electrons/charge/charge-electrons-000009.h5
examples/example_data/MS/DENSITY/electrons/charge/charge-electrons-000010.h5
examples/example_data/MS/DENSITY/electrons/charge/charge-electrons-000011.h5
examples/example_data/MS/DENSITY/electrons/charge/charge-electrons-000012.h5
examples/example_data/MS/DENSITY/electrons/charge/charge-electrons-000013.h5
examples/example_data/MS/DENSITY/electrons/charge/charge-electrons-000014.h5
examples/example_data/MS/DENSITY/electrons/charge/charge-electrons-000015.h5
examples/example_data/MS/DENSITY/electrons/charge/charge-electrons-000016.h5
osiris_utils-1.1.10.dist-info/licenses/LICENSE.txt
osiris_utils-1.1.10.dist-info/METADATA
osiris_utils-1.1.10.dist-info/WHEEL
osiris_utils-1.1.10.dist-info/top_level.txt
osiris_utils-1.1.10.dist-info/RECORD
