Metadata-Version: 2.4
Name: osiris_utils
Version: 1.1.10
Summary: Utilities to manipulate and visualise OSIRIS plasma PIC output data
Author-email: João Pedro Ferreira Biu <joaopedrofbiu@tecnico.ulisboa.pt>
License: MIT
Project-URL: Source Code, https://github.com/joaopedrobiu6/osiris_utils
Project-URL: Issues Tracker, https://github.com/joaopedrobiu6/osiris_utils/issues
Project-URL: Documentation, https://osiris-utils.readthedocs.io
Classifier: Development Status :: 3 - Alpha
Classifier: Intended Audience :: Science/Research
Classifier: License :: OSI Approved :: MIT License
Classifier: Natural Language :: English
Classifier: Programming Language :: Python :: 3
Classifier: Programming Language :: Python :: 3.8
Classifier: Programming Language :: Python :: 3.9
Classifier: Programming Language :: Python :: 3.10
Classifier: Programming Language :: Python :: 3.11
Classifier: Programming Language :: Python :: 3.12
Classifier: Topic :: Scientific/Engineering
Requires-Python: >=3.10
License-File: LICENSE.txt
Requires-Dist: numpy>=1.25
Requires-Dist: matplotlib>=3.8
Requires-Dist: pandas>=2.0
Requires-Dist: scipy>=1.11
Requires-Dist: h5py>=3.10
Requires-Dist: tqdm>=4.66
Provides-Extra: dev
Requires-Dist: pytest>=8.1; extra == "dev"
Requires-Dist: pytest-cov; extra == "dev"
Requires-Dist: pre-commit>=3.7; extra == "dev"
Requires-Dist: ruff>=0.4; extra == "dev"
Requires-Dist: isort>=5.13; extra == "dev"
Requires-Dist: types-tqdm; extra == "dev"
Requires-Dist: types-Pillow; extra == "dev"
Provides-Extra: docs
Requires-Dist: sphinx>=8; extra == "docs"
Requires-Dist: ipykernel; extra == "docs"
Requires-Dist: myst-parser; extra == "docs"
Requires-Dist: sphinx-copybutton<=0.5.2; extra == "docs"
Requires-Dist: sphinx-rtd-theme<3.0.3; extra == "docs"
Requires-Dist: sphinx-github-style<=1.2.2; extra == "docs"
Dynamic: license-file
